<?xml version="1.0" encoding="windows-1251"?>
<string_table>
  <string id="outfit_bandit_name">
    <rus>Бандитская куртка</rus>
  </string>
  <string id="outfit_stalker_tirex_name">
    <rus>Костюм Тирекса</rus>
  </string>
  <string id="outfit_stalker_tirex_description">
    <rus>Достоверно неизвестно, откуда этот костюм раздобыл Тирекс — один из ветеранов Зоны и боевик команды Призрака, но известно другое — Тирекс попал в засаду вояк на Агропроме. Тяжело раненный, был доставлен в южный комплекс. Лишь чудом ему удалось бежать, имея на руках ПМ и две обоймы патронов, в простом сталкерском комбинезоне. Остальной хабар Тирекса остался у военных. \nГлавная отличительная особенность этого костюма — возможность переносить значительно большее количество груза.</rus>
  </string>
  <string id="outfit_bandit_description">
    <rus>Традиционная одежда бандита — кожаная куртка со вшитыми броневыми элементами. Даёт защиту, крайне недостаточную в жёстких условиях Зоны.</rus>
  </string>
  <string id="outfit_bandit_name_m">
    <rus>Кольчужная куртка</rus>
  </string>
  <string id="outfit_bandit_description_m">
    <rus>Обычный слабенький бандитский бронежилет, но в подкладку вшито кольчужное полотно. Сделать такой под силу почти каждому, но терпения хватит далеко не всем.</rus>
  </string>
  <string id="outfit_bandit_veteran_name">
    <rus>Коричневый бандитский плащ</rus>
  </string>
  <string id="outfit_bandit_veteran_description">
    <rus>Имеет чуть большую защиту от ранений и огня, чем обычная куртка. Одежда "тёмных" ветеранов. Защита крайне недостаточна, но зато натуральная кожа.</rus>
  </string>
  <string id="outfit_bandit_master_name">
    <rus>Чёрный бандитский плащ</rus>
  </string>
  <string id="outfit_bandit_master_description">
    <rus>Сначала их носили "греховцы". Потом это стало отличительной чертой ОПГ Стрелка. Теперь в таких ходят бригадиры криминала. Неплохая пулестойкость... для плаща из натуральной кожи.</rus>
  </string>
  <string id="outfit_bandit_master_m">
    <rus>Плащ Борова</rus>
  </string>
  <string id="outfit_bandit_master_description_m">
    <rus>Единственный в своём роде плащ, принадлежавший главарю бандитов в Тёмной Долине. Грубая чёрная ткань с дополнительной подкладкой не только защищает от непогоды, но и будто бы впитывает окружающую тьму. По слухам, Боров носил его долгие годы, и он стал своего рода символом его власти. Возможно, дело в особом покрое или тщательно скрытых карманах с запасами провианта, но, облачаясь в этот плащ, его владелец быстрее восстанавливает силы, готовясь к новым тёмным делишкам.</rus>
  </string>
  <string id="outfit_exoskeleton_bandit_name">
    <rus>Экзоскелет бандитов</rus>
  </string>
  <string id="outfit_exoskeleton_bandit_slots_name">
    <rus>Экзоскелет бандитов — Расширенный</rus>
  </string>
  <string id="outfit_exoskeleton_bandit_plus_name">
    <rus>Экзоскелет бандитов — УВ-3</rus>
  </string>
  <string id="outfit_exoskeleton_bandit_slotsplus_name">
    <rus>Экзоскелет бандитов — Расширенный УВ-3</rus>
  </string>
  <string id="outfit_exoskeleton_bandit_description">
    <rus>Экзоскелет, производимый умельцами из группировки Борова под руководством Фраера. В таких экзоскелетах ходят только реальные пацаны на Зоне. Отличается надёжностью и высокой грузоподъёмностью.</rus>
  </string>
  <string id="outfit_exoskeleton_bandit_slots_description">
    <rus>Экзоскелет, производимый умельцами из группировки Борова под руководством Фраера. В таких экзоскелетах ходят только реальные пацаны на Зоне. Отличается надёжностью и высокой грузоподъёмностью.</rus>
  </string>
  <string id="outfit_dolg_name">
    <rus>ПСЗ-9Д "Броня Долга"</rus>
  </string>
  <string id="outfit_dolg_slots_name">
    <rus>ПСЗ-9Д "Броня Долга" — Расширенный</rus>
  </string>
  <string id="outfit_dolg_plus_name">
    <rus>ПСЗ-9Д "Броня Долга" — УВ-1</rus>
  </string>
  <string id="outfit_dolg_slotsplus_name">
    <rus>ПСЗ-9Д "Броня Долга" — Расширенный УВ-1</rus>
  </string>
  <string id="outfit_dolg_description">
    <rus>Производится одним из оборонных киевских НИИ на заказ группировки "Долг". Простота и надёжность базовой модели "ПСЗ-9" в сочетании с новыми материалами предоставляет хорошую защиту от различных вредных воздействий, включая огнестрельные повреждения. Из-за отсутствия системы защиты дыхания бронежилет требует доработки.</rus>
  </string>
  <string id="outfit_dolg_slots_description">
    <rus>Данный костюм производится одним из оборонных киевских НИИ на заказ группировки "Долг". Простота и надёжность базовой модели "ПСЗ-9" в сочетании с новыми материалами предоставляет хорошую защиту от различных вредных воздействий, включая огнестрельные повреждения. Из-за отсутствия системы защиты дыхания бронежилет требует доработки.</rus>
  </string>
  <string id="outfit_dolg_gaz_m1_name">
    <rus>ПСЗ-9Д-2 "Броня Долга" с противогазом</rus>
  </string>
  <string id="outfit_dolg_gaz_m1_slots_name">
    <rus>ПСЗ-9Д-2 "Броня Долга" с противогазом — Расширенный</rus>
  </string>
  <string id="outfit_dolg_gaz_m1_plus_name">
    <rus>ПСЗ-9Д-2 "Броня Долга" с противогазом — УВ-1</rus>
  </string>
  <string id="outfit_dolg_gaz_m1_slotsplus_name">
    <rus>ПСЗ-9Д-2 "Броня Долга" с противогазом — Расширенный УВ-1</rus>
  </string>
  <string id="outfit_dolg_gaz_m1_description">
    <rus>Данный костюм производится одним из оборонных киевских НИИ на заказ группировки "Долг". Основан на базовой модели "ПСЗ-9". Предоставляет хорошую защиту от различных вредных воздействий, включая огнестрельные повреждения. В этой модификации доработана система дыхания.</rus>
  </string>
  <string id="outfit_dolg_gaz_m1_slots_description">
    <rus>Данный костюм производится одним из оборонных киевских НИИ на заказ группировки "Долг". Основан на базовой модели "ПСЗ-9". Предоставляет хорошую защиту от различных вредных воздействий, включая огнестрельные повреждения. В этой модификации доработана система дыхания.</rus>
  </string>
  <string id="outfit_dolg_name_m1">
    <rus>ПСЗ-9Д "Охотничий"</rus>
  </string>
  <string id="outfit_dolg_m1_slots_name">
    <rus>ПСЗ-9Д "Охотничий" — Расширенный</rus>
  </string>
  <string id="outfit_dolg_m1_plus_name">
    <rus>ПСЗ-9Д "Охотничий" — УВ-1</rus>
  </string>
  <string id="outfit_dolg_m1_slotsplus_name">
    <rus>ПСЗ-9Д "Охотничий" — Расширенный УВ-1</rus>
  </string>
  <string id="outfit_dolg_description_m1">
    <rus>"Долговский" бронекостюм с улучшенной защитой от укусов и порезов.</rus>
  </string>
  <string id="outfit_dolg_slots_description_m1">
    <rus>"Долговский" бронекостюм с улучшенной защитой от укусов и порезов.</rus>
  </string>
  <string id="outfit_scientific_dolg_name">
    <rus>ПСЗ-9МД "Универсальная защита"</rus>
  </string>
  <string id="outfit_scientific_dolg_slots_name">
    <rus>ПСЗ-9МД "Универсальная защита" — Расширенный</rus>
  </string>
  <string id="outfit_scientific_dolg_plus_name">
    <rus>ПСЗ-9МД "Универсальная защита" — УВ-2</rus>
  </string>
  <string id="outfit_scientific_dolg_slotsplus_name">
    <rus>ПСЗ-9МД "Универсальная защита" — Расширенный УВ-2</rus>
  </string>
  <string id="outfit_scientific_dolg_description">
    <rus>Отличный защитный костюм для Зоны. Сталкеры ценят его за сочетание отличных противоаномальных качеств и противопулевой защиты. В составе: комбинезон "ПСЗ-9д", система дыхания с замкнутым циклом, встроенная система подавления действия аномальных полей. Предоставляет качественную защиту от пулевого и осколочного попадания.</rus>
  </string>
  <string id="outfit_scientific_dolg_slots_description">
    <rus>Отличный защитный костюм для Зоны. Сталкеры ценят его за сочетание отличных противоаномальных качеств и противопулевой защиты. В составе: комбинезон "ПСЗ-9д", система дыхания с замкнутым циклом, встроенная система подавления действия аномальных полей. Предоставляет качественную защиту от пулевого и осколочного попадания.</rus>
  </string>
  <string id="outfit_exoskeleton_dolg_name">
    <rus>Экзоскелет "Долга"</rus>
  </string>
  <string id="outfit_exoskeleton_dolg_slots_name">
    <rus>Экзоскелет "Долга" — Расширенный</rus>
  </string>
  <string id="outfit_exoskeleton_dolg_plus_name">
    <rus>Экзоскелет "Долга" — УВ-3</rus>
  </string>
  <string id="outfit_exoskeleton_dolg_slotsplus_name">
    <rus>Экзоскелет "Долга" — Расширенный УВ-3</rus>
  </string>
  <string id="outfit_exoskeleton_dolg_description">
    <rus>Отечественная разработка одного из НИИ, специально для группировки "Долг". Боевые функции преобладают, плюс большая грузоподъёмность. Большой вес костюма, однако, не исключает возможности бега в нём.</rus>
  </string>
  <string id="outfit_exoskeleton_dolg_slots_description">
    <rus>Отечественная разработка одного из НИИ, специально для группировки "Долг". Боевые функции преобладают, плюс большая грузоподъёмность. Большой вес костюма, однако, не исключает возможности бега в нём.</rus>
  </string>
  <string id="outfit_scientific_ecolog_name">
    <rus>Комбинезон ССП-99 "Эколог"</rus>
  </string>
  <string id="outfit_scientific_ecolog_slots_name">
    <rus>Комбинезон ССП-99 "Эколог" — Расширенный</rus>
  </string>
  <string id="outfit_scientific_ecolog_plus_name">
    <rus>Комбинезон ССП-99 "Эколог" — УВ-1</rus>
  </string>
  <string id="outfit_scientific_ecolog_slotsplus_name">
    <rus>Комбинезон ССП-99 "Эколог" — Расширенный УВ-1</rus>
  </string>
  <string id="outfit_scientific_ecolog_description">
    <rus>Созданный для работы в условиях Зоны костюм химической защиты серии "ССП-99". Используется экспедициями учёных и сотрудничающих с ними сталкеров-экологов. Встроенная система фильтрации воздуха и кондиционирования. Не рассчитан на ведение боевых действий.</rus>
  </string>
  <string id="outfit_scientific_ecolog_slots_description">
    <rus>Созданный для работы в условиях Зоны костюм химической защиты серии "ССП-99". Используется экспедициями учёных и сотрудничающих с ними сталкеров-экологов. Встроенная система фильтрации воздуха и кондиционирования. Не рассчитан на ведение боевых действий.</rus>
  </string>
  <string id="outfit_scientific_protection_name">
    <rus>Комбинезон ССП-99М "Вега"</rus>
  </string>
  <string id="outfit_scientific_protection_slots_name">
    <rus>Комбинезон ССП-99М "Вега" — Расширенный</rus>
  </string>
  <string id="outfit_scientific_protection_plus_name">
    <rus>Комбинезон ССП-99М "Вега" — УВ-2</rus>
  </string>
  <string id="outfit_scientific_protection_slotsplus_name">
    <rus>Комбинезон ССП-99М "Вега" — Расширенный УВ-2</rus>
  </string>
  <string id="outfit_scientific_protection_description">
    <rus>Высококачественный модифицированный комбинезон серии "ССП-99". Добавлена защита торса от пулевого и осколочного повреждения. Предназначен для экипировки охраны научных экспедиций. Эффективная защита от радиации и биологических аномалий. Стоек к химически-агрессивным средам и другим, вредным для организма воздействиям.</rus>
  </string>
  <string id="outfit_scientific_protection_slots_description">
    <rus>Высококачественный модифицированный комбинезон серии "ССП-99". Добавлена защита торса от пулевого и осколочного повреждения. Предназначен для экипировки охраны научных экспедиций. Эффективная защита от радиации и биологических аномалий. Стоек к химически-агрессивным средам и другим, вредным для организма воздействиям.</rus>
  </string>
  <string id="outfit_soldier_name">
    <rus>Армейский бронежилет</rus>
  </string>
  <string id="outfit_soldier_plus_name">
    <rus>Армейский бронежилет — УВ-1</rus>
  </string>
  <string id="outfit_soldier_slots_name">
    <rus>Армейский бронежилет — Расширенный</rus>
  </string>
  <string id="outfit_soldier_slotsplus_name">
    <rus>Армейский бронежилет — Расширенный УВ-1</rus>
  </string>
  <string id="outfit_soldier_description">
    <rus>Стандартный комплект снаряжения солдата — лёгкий армейский бронежилет. Достаточно эффективно защищает от пуль мелкого калибра и осколков. Неэффективен против аномальных и других воздействий.</rus>
  </string>
  <string id="outfit_soldier_slots_description">
    <rus>Стандартный комплект снаряжения солдата — лёгкий армейский бронежилет. Достаточно эффективно защищает от пуль мелкого калибра и осколков. Неэффективен против аномальных и других воздействий.</rus>
  </string>
  <string id="outfit_specops_name">
    <rus>Бронекостюм "Берилл-5М"</rus>
  </string>
  <string id="outfit_specops_slots_name">
    <rus>Бронекостюм "Берилл-5М" — Расширенный</rus>
  </string>
  <string id="outfit_specops_plus_name">
    <rus>Бронекостюм "Берилл-5М" — УВ-1</rus>
  </string>
  <string id="outfit_specops_slotsplus_name">
    <rus>Бронекостюм "Берилл-5М" — Расширенный УВ-1</rus>
  </string>
  <string id="outfit_specops_description">
    <rus>Модифицированная для работы в условиях Зоны, экипировка армейского спецназа — "Берилл-5М". В составе: армейский бронежилет серии "ПСЗ-9а" с бериллиевым напылением. Предназначен для штурмовых операций в областях с повышенным радиационным фоном. Слабоэффективен в условиях высокой аномальной активности.</rus>
  </string>
  <string id="outfit_specops_slots_description">
    <rus>Модифицированная для работы в условиях Зоны, экипировка армейского спецназа — "Берилл-5М". В составе: армейский бронежилет серии "ПСЗ-9а" с бериллиевым напылением. Предназначен для штурмовых операций в областях с повышенным радиационным фоном. Слабоэффективен в условиях высокой аномальной активности.</rus>
  </string>
  <string id="specnaz_outfit_name_m1">
    <rus>Лечебный "Берилл"</rus>
  </string>
  <string id="specnaz_outfit_m1_slots_name">
    <rus>Лечебный "Берилл" — Расширенный</rus>
  </string>
  <string id="specnaz_outfit_m1_plus_name">
    <rus>Лечебный "Берилл" — УВ-1</rus>
  </string>
  <string id="specnaz_outfit_m1_slotsplus_name">
    <rus>Лечебный "Берилл" — Расширенный УВ-1</rus>
  </string>
  <string id="specnaz_outfit_description_m1">
    <rus>Обычный бронежилет армейского спецназа, ткань которого пропитана стрептоцидовой мазью, ускоряющей заживление ран.</rus>
  </string>
  <string id="specnaz_outfit_slots_description_m1">
    <rus>Обычный бронежилет армейского спецназа, ткань которого пропитана стрептоцидовой мазью, ускоряющей заживление ран.</rus>
  </string>
  <string id="outfit_military_name">
    <rus>Армейский "СКАТ-9М"</rus>
  </string>
  <string id="outfit_military_slots_name">
    <rus>Армейский "СКАТ-9М" — Расширенный</rus>
  </string>
  <string id="outfit_military_plus_name">
    <rus>Армейский "СКАТ-9М" — УВ-2</rus>
  </string>
  <string id="outfit_military_slotsplus_name">
    <rus>Армейский "СКАТ-9М" — Расширенный УВ-2</rus>
  </string>
  <string id="outfit_military_description">
    <rus>Армейский бронекостюм "СКАТ-9М" создан для проведений штурмовых операций в зонах активности аномалий. В составе: тяжёлый армейский бронекостюм серии "ПСЗ-12п" и встроенный компенсационный костюм. Предоставляет великолепную защиту от пулевого и осколочного попадания, при этом не снижая подвижности солдата. В наличии сбалансированная система защиты от аномального воздействия.</rus>
  </string>
  <string id="outfit_military_slots_description">
    <rus>Армейский бронекостюм "СКАТ-9М" создан для проведений штурмовых операций в зонах активности аномалий. В составе: тяжёлый армейский бронекостюм серии "ПСЗ-12п" и встроенный компенсационный костюм. Предоставляет великолепную защиту от пулевого и осколочного попадания, при этом не снижая подвижности солдата. В наличии сбалансированная система защиты от аномального воздействия.</rus>
  </string>
  <string id="outfit_militaryspec_name">
    <rus>Армейский "СКАТ-10"</rus>
  </string>
  <string id="outfit_militaryspec_slots_name">
    <rus>Армейский "СКАТ-10" — Расширенный</rus>
  </string>
  <string id="outfit_militaryspec_plus_name">
    <rus>Армейский "СКАТ-10" — УВ-3</rus>
  </string>
  <string id="outfit_militaryspec_slotsplus_name">
    <rus>Армейский "СКАТ-10" — Расширенный УВ-3</rus>
  </string>
  <string id="outfit_militaryspec_description">
    <rus>Армейский специальный бронекостюм "СКАТ-10" создан на базе хорошо зарекомендовавшего себя в условиях Зоны "СКАТ-9М". Идеально подходит для проведений штурмовых операций в зонах активности аномалий. В составе: тяжёлый армейский бронекостюм серии "ПСЗ-12СА" и встроенный компенсационный костюм. Предоставляет великолепную защиту от пулевого и осколочного попадания, при этом не снижая подвижности солдата. В наличии также отличная система защиты от аномального воздействия.</rus>
  </string>
  <string id="outfit_militaryspec_slots_description">
    <rus>Армейский специальный бронекостюм "СКАТ-10" создан на базе хорошо зарекомендовавшего себя в условиях Зоны "СКАТ-9М". Идеально подходит для проведений штурмовых операций в зонах активности аномалий. В составе: тяжёлый армейский бронекостюм серии "ПСЗ-12СА" и встроенный компенсационный костюм. Предоставляет великолепную защиту от пулевого и осколочного попадания, при этом не снижая подвижности солдата. В наличии также отличная система защиты от аномального воздействия.</rus>
  </string>
  <string id="outfit_exoskeleton_stalker_name">
    <rus>Экзоскелет сталкеров</rus>
  </string>
  <string id="outfit_exoskeleton_stalker_slots_name">
    <rus>Экзоскелет сталкеров — Расширенный</rus>
  </string>
  <string id="outfit_exoskeleton_stalker_plus_name">
    <rus>Экзоскелет сталкеров — УВ-3</rus>
  </string>
  <string id="outfit_exoskeleton_stalker_slotsplus_name">
    <rus>Экзоскелет сталкеров — Расширенный УВ-3</rus>
  </string>
  <string id="outfit_exoskeleton_stalker_description">
    <rus>Экспериментальный образец военного экзоскелета. В серийное производство так и не попал, ввиду чрезвычайной дороговизны и некоторых ошибок в проектировании. Не смотря на это, выпускается малыми партиями на подпольных предприятиях за пределами Украины. Данный экзоскелет относится к третьему поколению. В нём устранены конструктивные недостатки, кардинально снижавшие подвижность, а также усилена броня. Предоставляет великолепную защиту от пулевого и осколочного попадания, но не гарантирует стойкости к аномальным воздействиям.</rus>
  </string>
  <string id="outfit_exoskeleton_stalker_slots_description">
    <rus>Экспериментальный образец военного экзоскелета. В серийное производство так и не попал, ввиду чрезвычайной дороговизны и некоторых ошибок в проектировании. Не смотря на это, выпускается малыми партиями на подпольных предприятиях за пределами Украины. Данный экзоскелет относится к третьему поколению. В нём устранены конструктивные недостатки, кардинально снижавшие подвижность, а также усилена броня. Предоставляет великолепную защиту от пулевого и осколочного попадания, но не гарантирует стойкости к аномальным воздействиям.</rus>
  </string>
  <string id="outfit_exoskeleton_stalker_name_m1">
    <rus>Модифицированный экзоскелет</rus>
  </string>
  <string id="outfit_exoskeleton_stalker_m1_slots_name">
    <rus>Модифицированный экзоскелет — Расширенный</rus>
  </string>
  <string id="outfit_exoskeleton_stalker_m1_plus_name">
    <rus>Модифицированный экзоскелет — УВ-3</rus>
  </string>
  <string id="outfit_exoskeleton_stalker_m1_slotsplus_name">
    <rus>Модифицированный экзоскелет — Расширенный УВ-3</rus>
  </string>
  <string id="outfit_exoskeleton_stalker_description_m1">
    <rus>
        Переделанная версия стандартного сталкерского экзоскелета, улучшенная для более удобного использования в условиях Зоны. В конструкции добавлен дополнительный контейнер для артефактов и слот для быстрого использования предметов, а также немного доработана система привода, что позволило увеличить грузоподъёмность без сильной потери подвижности.</rus>
  </string>
  <string id="outfit_exoskeleton_stalker_slots_description_m1">
    <rus>
        Экспериментальный образец военного экзоскелета (модифицированный).</rus>
  </string>
  <string id="outfit_killer_name">
    <rus>Комбинезон наёмника</rus>
  </string>
  <string id="outfit_killer_plus_name">
    <rus>Комбинезон наёмника — УВ-1</rus>
  </string>
  <string id="outfit_killer_slots_name">
    <rus>Комбинезон наёмника — Расширенный</rus>
  </string>
  <string id="outfit_killer_slotsplus_name">
    <rus>Комбинезон наёмника — Расширенный УВ-1</rus>
  </string>
  <string id="outfit_killer_description">
    <rus>Комбинезон сталкера из группировки наёмников. За основу взяты образцы экипировки спецназа западных армий. За счёт специальной обработки ткани усилена устойчивость брони при физическом смещении пластин. По защитным характеристикам немного превосходит армейские бронежилеты серии "ПСЗ-7".</rus>
  </string>
  <string id="outfit_killer_slots_description">
    <rus>Комбинезон сталкера из группировки наёмников. За основу взяты образцы экипировки спецназа западных армий. За счёт специальной обработки ткани усилена устойчивость брони при физическом смещении пластин. По защитным характеристикам немного превосходит армейские бронежилеты серии "ПСЗ-7".</rus>
  </string>
  <string id="outfit_killer_name_m1">
    <rus>Комбинезон Волкодава</rus>
  </string>
  <string id="outfit_killer_m1_plus_name">
    <rus>Комбинезон Волкодава — УВ-1</rus>
  </string>
  <string id="outfit_killer_m1_slots_name">
    <rus>Комбинезон Волкодава — Расширенный</rus>
  </string>
  <string id="outfit_killer_m1_slotsplus_name">
    <rus>Комбинезон Волкодава — Расширенный УВ-1</rus>
  </string>
  <string id="outfit_killer_description_m1">
    <rus>Переделанный комбинезон наёмника, который принадлежал самому Волкодаву — опытному бойцу, чьё имя наводило страх на многих сталкеров. Внутри подкладки скрыта кольчужная сетка, дающая дополнительную защиту от пуль и когтей мутантов.</rus>
  </string>
  <string id="outfit_killer_slots_description_m1">
    <rus>С виду всё тот же обычный комбинезон наёмников, но с явным отличием внутри — в подкладку куртки вшита кольчужная сетка, повышающая защиту от огнестрельного оружия, а также от укусов мутантов.</rus>
  </string>
  <string id="outfit_scientific_killer_name">
    <rus>Научный костюм наёмников</rus>
  </string>
  <string id="outfit_scientific_killer_slots_name">
    <rus>Научный костюм наёмников — Расширенный</rus>
  </string>
  <string id="outfit_scientific_killer_plus_name">
    <rus>Научный костюм наёмников — УВ-2</rus>
  </string>
  <string id="outfit_scientific_killer_slotsplus_name">
    <rus>Научный костюм наёмников — Расширенный УВ-2</rus>
  </string>
  <string id="outfit_scientific_killer_description">
    <rus>Костюм наёмников, которые промышляют в аномальных зонах. Система защиты с замкнутым циклом, плюс встроенная система подавления действия аномальных полей. Предоставляет неплохую защиту от пулевого и осколочного попадания, но явно недостаточную для масштабных боевых действий.</rus>
  </string>
  <string id="outfit_scientific_killer_slots_description">
    <rus>Костюм наёмников, которые промышляют в аномальных зонах. Система защиты с замкнутым циклом, плюс встроенная система подавления действия аномальных полей. Предоставляет неплохую защиту от пулевого и осколочного попадания, но явно недостаточную для масштабных боевых действий.</rus>
  </string>
  <string id="outfit_exoskeleton_killer_name">
    <rus>Экзоскелет наёмников</rus>
  </string>
  <string id="outfit_exoskeleton_killer_slots_name">
    <rus>Экзоскелет наёмников — Расширенный</rus>
  </string>
  <string id="outfit_exoskeleton_killer_plus_name">
    <rus>Экзоскелет наёмников — УВ-3</rus>
  </string>
  <string id="outfit_exoskeleton_killer_slotsplus_name">
    <rus>Экзоскелет наёмников — Расширенный УВ-3</rus>
  </string>
  <string id="outfit_exoskeleton_killer_description">
    <rus>Экспериментальный образец военного экзоскелета западного производства. Данный экземпляр относится к третьему поколению. Используется наёмниками. Упор сделан на боевое применение, аномальная устойчивость низкая. Режим бега активирован.</rus>
  </string>
  <string id="outfit_exoskeleton_killer_slots_description">
    <rus>Экспериментальный образец военного экзоскелета западного производства. Данный экземпляр относится к третьему поколению. Используется наёмниками. Упор сделан на боевое применение, аномальная устойчивость низкая. Режим бега активирован.</rus>
  </string>
  <string id="outfit_monolit_name">
    <rus>Комбинезон "Монолита"</rus>
  </string>
  <string id="outfit_monolit_slots_name">
    <rus>Комбинезон "Монолита" — Расширенный</rus>
  </string>
  <string id="outfit_monolit_plus_name">
    <rus>Комбинезон "Монолита" — УВ-1</rus>
  </string>
  <string id="outfit_monolit_slotsplus_name">
    <rus>Комбинезон "Монолита" — Расширенный УВ-1</rus>
  </string>
  <string id="outfit_monolit_description">
    <rus>Комбинезон сталкера группировки "Монолит", производитель неизвестен. По защитным характеристикам немного уступает армейскому бронежилету серии "ПСЗ-9а". По структуре напоминает широко распространённые среди нейтральных сталкеров комбинезоны, в которых бронежилет соединяется с костюмом противорадиационной защиты. Неплохо защищает от слабого стрелкового оружия. Уровень защиты от аномальной активности оставляет желать лучшего из-за отсутствия системы фильтрации воздуха.</rus>
  </string>
  <string id="outfit_monolit_slots_description">
    <rus>Комбинезон сталкера группировки "Монолит", производитель неизвестен. По защитным характеристикам немного уступает армейскому бронежилету серии "ПСЗ-9а". По структуре напоминает широко распространённые среди нейтральных сталкеров комбинезоны, в которых бронежилет соединяется с костюмом противорадиационной защиты. Неплохо защищает от слабого стрелкового оружия. Уровень защиты от аномальной активности оставляет желать лучшего из-за отсутствия системы фильтрации воздуха.</rus>
  </string>
  <string id="outfit_scientific_monolit_name">
    <rus>Научный костюм "Монолита"</rus>
  </string>
  <string id="outfit_scientific_monolit_slots_name">
    <rus>Научный костюм "Монолита" — Расширенный</rus>
  </string>
  <string id="outfit_scientific_monolit_plus_name">
    <rus>Научный костюм "Монолита" — УВ-2</rus>
  </string>
  <string id="outfit_scientific_monolit_slotsplus_name">
    <rus>Научный костюм "Монолита" — Расширенный УВ-2</rus>
  </string>
  <string id="outfit_scientific_monolit_description">
    <rus>Как и большинство творений "Монолита" — технология создания данного костюма неизвестна. Установлено, что в состав входят внеземные материалы, которые более лёгкие, чем их земные аналоги, и очень хорошо защищают от радиации. В остальном характеристики схожи с обычными научными костюмами.</rus>
  </string>
  <string id="outfit_scientific_monolit_slots_description">
    <rus>Как и большинство творений "Монолита" — технология создания данного костюма неизвестна. Установлено, что в состав входят внеземные материалы, которые более лёгкие, чем их земные аналоги, и очень хорошо защищают от радиации. В остальном характеристики схожи с обычными научными костюмами.</rus>
  </string>
  <string id="outfit_exoskeleton_monolit_name">
    <rus>Экзоскелет "Монолита"</rus>
  </string>
  <string id="outfit_exoskeleton_monolit_slots_name">
    <rus>Экзоскелет "Монолита" — Расширенный</rus>
  </string>
  <string id="outfit_exoskeleton_monolit_plus_name">
    <rus>Экзоскелет "Монолита" — УВ-1</rus>
  </string>
  <string id="outfit_exoskeleton_monolit_slotsplus_name">
    <rus>Экзоскелет "Монолита" — Расширенный УВ-3</rus>
  </string>
  <string id="outfit_exoskeleton_monolit_description">
    <rus>Технология создания данного экзоскелета покрыта тайной. В составе материала обнаружены вкрапления неизвестного металла, природа происхождения которого не ясна. Удивительно малый вес и высокие равные показатели по всем пунктам. Максимальная защита от радиации. Функция бега активирована.</rus>
  </string>
  <string id="outfit_exoskeleton_monolit_slots_description">
    <rus>Технология создания данного экзоскелета покрыта тайной. В составе материала обнаружены вкрапления неизвестного металла, природа происхождения которого не ясна. Удивительно малый вес и высокие равные показатели по всем пунктам. Максимальная защита от радиации. Функция бега активирована.</rus>
  </string>
  <string id="outfit_novice_name">
    <rus>Тканевая куртка</rus>
  </string>
  <string id="outfit_novice_description">
    <rus>Самая простая и доступная одежда для тех, кто только ступил на тропу сталкера. Лёгкая, удобная и неприхотливая в уходе, она лишь номинально защищает от внешних угроз. Капюшон спасает от дождя, а плотная ткань хоть немного смягчает удары веток и мелкие порезы. Однако против аномалий, пуль и когтей мутантов такая экипировка практически бесполезна. Часто используется новичками, которым пока не по карману что-то более серьёзное.</rus>
  </string>
  <string id="outfit_novice_leather_name">
    <rus>Кожаная куртка</rus>
  </string>
  <string id="outfit_novice_leather_description">
    <rus>Обычная плотная кожаная куртка, каких много. Несколько прочнее обычной тканевой куртки. Слегка усиливает противопулевую и осколочную защиту. Неэффективна против аномальных и других воздействий.</rus>
  </string>
  <string id="outfit_rain_name">
    <rus>Кожанный плащ</rus>
  </string>
  <string id="outfit_rain_description">
    <rus>Самый обыкновенный плащ. Слегка усиливает противопулевую и осколочную защиту. Неэффективен против аномальных и других воздействий.</rus>
  </string>
  <string id="outfit_novice_name_m">
    <rus>Аномальная кожанка</rus>
  </string>
  <string id="outfit_novice_description_m">
    <rus>Эту куртку сняли с трупа одного из сталкеров, умершего в "Киселе". Пролежав долгое время в аномалии, куртка обрела свойство ускорять метаболизм.</rus>
  </string>
  <string id="outfit_stalker_name">
    <rus>Комбинезон сталкера</rus>
  </string>
  <string id="outfit_stalker_slots_name">
    <rus>Комбинезон сталкера — Расширенный</rus>
  </string>
  <string id="outfit_stalker_plus_name">
    <rus>Комбинезон сталкера — УВ-1</rus>
  </string>
  <string id="outfit_stalker_slotsplus_name">
    <rus>Комбинезон сталкера — Расширенный УВ-1</rus>
  </string>
  <string id="outfit_stalker_description">
    <rus>Производимый "народными умельцами" комбинезон сталкера представляет собой эффективное сочетание лёгкого армейского бронежилета и комбинезона из прорезиненной ткани. Усилен за счёт встроенных кевларовых пластин. Неплохо защищает от слабого стрелкового оружия. В целом, крайне недостаточен для глубоких рейдов и серьёзных операций в узлах Зоны.</rus>
  </string>
  <string id="outfit_stalker_slots_description">
    <rus>Производимый "народными умельцами" комбинезон сталкера представляет собой эффективное сочетание лёгкого армейского бронежилета и комбинезона из прорезиненной ткани. Усилен за счёт встроенных кевларовых пластин. Неплохо защищает от слабого стрелкового оружия. В целом, крайне недостаточен для глубоких рейдов и серьёзных операций в узлах Зоны.</rus>
  </string>
  <string id="outfit_stalker_v1_name">
    <rus>Комбинезон сталкера "Ветеран-1"</rus>
  </string>
  <string id="outfit_stalker_v1_slots_name">
    <rus>Комбинезон сталкера "Ветеран-1" — Расширенный</rus>
  </string>
  <string id="outfit_stalker_v1_plus_name">
    <rus>Комбинезон сталкера "Ветеран-1" — УВ-1</rus>
  </string>
  <string id="outfit_stalker_v1_slotsplus_name">
    <rus>Комбинезон сталкера "Ветеран-1" — Расширенный УВ-1</rus>
  </string>
  <string id="outfit_stalker_v1_description">
    <rus>Производимые "народными умельцами" комбинезоны сталкера серии "Ветеран" представляют собой эффективное сочетание лёгкого армейского бронежилета и комбинезона из прорезиненной ткани. Также они усилены за счёт встроенных кевларовых пластин. Неплохо защищают от слабого стрелкового оружия. В целом, крайне недостаточны для глубоких рейдов и серьёзных операций в узлах Зоны. В данном образце акцентирована защита от химических ожогов (несколько в ущерб к защите от открытого огня и электричества).</rus>
  </string>
  <string id="outfit_stalker_v2_name">
    <rus>Комбинезон сталкера "Ветеран-2"</rus>
  </string>
  <string id="outfit_stalker_v2_slots_name">
    <rus>Комбинезон сталкера "Ветеран-2" — Расширенный</rus>
  </string>
  <string id="outfit_stalker_v2_plus_name">
    <rus>Комбинезон сталкера "Ветеран-2" — УВ-1</rus>
  </string>
  <string id="outfit_stalker_v2_slotsplus_name">
    <rus>Комбинезон сталкера "Ветеран-2" — Расширенный УВ-1</rus>
  </string>
  <string id="outfit_stalker_v2_description">
    <rus>Производимые "народными умельцами" комбинезоны сталкера серии "Ветеран" представляют собой эффективное сочетание лёгкого армейского бронежилета и комбинезона из прорезиненной ткани. Также они усилены за счёт встроенных кевларовых пластин. Неплохо защищают от слабого стрелкового оружия. В целом, крайне недостаточны для глубоких рейдов и серьёзных операций в узлах Зоны. В данном образце акцентирована защита от электричества (несколько в ущерб к защите от химического ожога и открытого огня) и несколько усилена бронезащита конечностей.</rus>
  </string>
  <string id="outfit_stalker_v3_name">
    <rus>Комбинезон сталкера "Ветеран-3"</rus>
  </string>
  <string id="outfit_stalker_v3_slots_name">
    <rus>Комбинезон сталкера "Ветеран-3" — Расширенный</rus>
  </string>
  <string id="outfit_stalker_v3_plus_name">
    <rus>Комбинезон сталкера "Ветеран-3" — УВ-1</rus>
  </string>
  <string id="outfit_stalker_v3_slotsplus_name">
    <rus>Комбинезон сталкера "Ветеран-3" — Расширенный УВ-1</rus>
  </string>
  <string id="outfit_stalker_v3_description">
    <rus>Производимые "народными умельцами" комбинезоны сталкера серии "Ветеран" представляют собой эффективное сочетание лёгкого армейского бронежилета и комбинезона из прорезиненной ткани. Также они усилены за счёт встроенных кевларовых пластин. Неплохо защищают от слабого стрелкового оружия. В целом, крайне недостаточны для глубоких рейдов и серьёзных операций в узлах Зоны. В данном образце акцентирована защита от открытого огня (несколько в ущерб к защите от химического ожога и электричества), несколько усилена бронезащита конечностей и заметно усилена бронезащита корпуса.</rus>
  </string>
  <string id="outfit_stalker_v4_name">
    <rus>Комбинезон КОУ-1 "Спектр"</rus>
  </string>
  <string id="outfit_stalker_v4_slots_name">
    <rus>Комбинезон КОУ-1 "Спектр" — Расширенный</rus>
  </string>
  <string id="outfit_stalker_v4_plus_name">
    <rus>Комбинезон КОУ-1 "Спектр" — УВ-1</rus>
  </string>
  <string id="outfit_stalker_v4_slotsplus_name">
    <rus>Комбинезон КОУ-1 "Спектр" — Расширенный УВ-1</rus>
  </string>
  <string id="outfit_stalker_v4_description">
    <rus>Комбинезон Охраны Учёных — это сталкерский костюм, первоначально разработанный для охраны научных групп в Зоне. Он сочетает в себе лёгкий бронежилет и прорезиненный материалчто обеспечивает защиту не только от влаги и агрессивных воздействий аномалий, но и от химических ожогов и электрических разрядов. Встроенные кевларовые пластины дают умеренную защиту от лёгкого стрелкового оружия, а специальная пропитка снижает риск возгорания. Несмотря на свою эффективность, костюм не предназначен для затяжных рейдов и активных боевых столкновений, поэтому чаще всего используется для патрулирования периметра научных лагерей и сопровождения исследовательских экспедиций.</rus>
  </string>
  <string id="outfit_stalker_name_m3">
    <rus>Комбинезон Стрелка</rus>
  </string>
  <string id="outfit_stalker_uniq_slots_name">
    <rus>Комбинезон Стрелка — Расширенный</rus>
  </string>
  <string id="outfit_stalker_uniq_plus_name">
    <rus>Комбинезон Стрелка — УВ-1</rus>
  </string>
  <string id="outfit_stalker_uniq_slotsplus_name">
    <rus>Комбинезон Стрелка — Расширенный УВ-1</rus>
  </string>
  <string id="outfit_stalker_description_m3">
    <rus>Уникальный комбинезон легендарного сталкера по прозвищу Стрелок. Обладает повышенной стойкостью к различным повреждениям и, как следствие, уменьшенным износом. Способен медленно восстанавливать здоровье владельца. Механизм этого явления не ясен — подкладка брони не пропитана ни каким целебным составом. Как и кто преобразовал обычный комбез в это чудо — неизвестно...</rus>
  </string>
  <string id="outfit_stalker_slots_description_m3">
    <rus>Уникальный комбинезон легендарного сталкера по прозвищу Стрелок. Обладает повышенной стойкостью к различным повреждениям и, как следствие, уменьшенным износом. Способен медленно восстанавливать здоровье владельца. Механизм этого явления не ясен — подкладка брони не пропитана ни каким целебным составом. Как и кто преобразовал обычный комбез в это чудо — неизвестно...</rus>
  </string>
  <string id="outfit_stalker_guard_name">
    <rus>Лёгкий комбинезон сталкера</rus>
  </string>
  <string id="outfit_stalker_guard_slots_name">
    <rus>Лёгкий комбинезон сталкера — Расширенный</rus>
  </string>
  <string id="outfit_stalker_guard_plus_name">
    <rus>Лёгкий комбинезон сталкера — УВ-1</rus>
  </string>
  <string id="outfit_stalker_guard_slotsplus_name">
    <rus>Лёгкий комбинезон сталкера — Расширенный УВ-1</rus>
  </string>
  <string id="outfit_stalker_guard_description">
    <rus>Лёгкий вариант комбинезона сталкера. Представляет собой лёгкий кевларовый бронежилет, усиленный бронепластинами из особопрочной высоколегированной стали, благодаря чему при меньшем весе неплохо защищает от стрелкового оружия. От радиации и аномальных воздействий почти не защищает. Стоит недорого, но нигде не продаётся. Как попал в Зону — неизвестно. Используется охраной в баре.</rus>
  </string>
  <string id="outfit_stalker_guard_slots_description">
    <rus>Лёгкий вариант комбинезона сталкера. Представляет собой лёгкий кевларовый бронежилет, усиленный бронепластинами из особопрочной высоколегированной стали, благодаря чему при меньшем весе неплохо защищает от стрелкового оружия. От радиации и аномальных воздействий почти не защищает. Стоит недорого, но нигде не продаётся. Как попал в Зону — неизвестно. Используется охраной в баре.</rus>
  </string>
  <string id="outfit_stalker_name_m1">
    <rus>Комбинезон Призрака</rus>
  </string>
  <string id="outfit_stalker_m1_slots_name">
    <rus>Комбинезон Призрака — Расширенный</rus>
  </string>
  <string id="outfit_stalker_m1_plus_name">
    <rus>Комбинезон Призрака — УВ-1</rus>
  </string>
  <string id="outfit_stalker_m1_slotsplus_name">
    <rus>Комбинезон Призрака — Расширенный УВ-1</rus>
  </string>
  <string id="outfit_stalker_description_m1">
    <rus>Ходят легенды о том, что призрачный сталкер никогда не носит с собой аптечки. Всё на нём заживает, как на собаке. Говорят, что у него необычный комбинезон, который он умудрился достать из какой-то аномалии.</rus>
  </string>
  <string id="outfit_stalker_slots_description_m1">
    <rus>Ходят легенды о том, что призрачный сталкер никогда не носит с собой аптечки. Всё на нём заживает, как на собаке. Говорят, что у него необычный комбинезон, который он умудрился достать из какой-то аномалии.</rus>
  </string>
  <string id="outfit_stalker_name_m2">
    <rus>Комбинезон туриста</rus>
  </string>
  <string id="outfit_stalker_m2_slots_name">
    <rus>Комбинезон туриста — Расширенный</rus>
  </string>
  <string id="outfit_stalker_m2_plus_name">
    <rus>Комбинезон туриста — УВ-1</rus>
  </string>
  <string id="outfit_stalker_m2_slotsplus_name">
    <rus>Комбинезон туриста — Расширенный УВ-1</rus>
  </string>
  <string id="outfit_stalker_description_m2">
    <rus>Бывший хозяин этой вещи был настоящим туристом и, видать, не раз хаживал в нём в тяжёлые, на грани человеческих возможностей, походы. Он знал, как правильно распределить груз, который нёс, и каким вещам отдать предпочтение. Карманы на куртке и грамотно подобранный рюкзак позволяют нести больший вес.</rus>
  </string>
  <string id="outfit_stalker_slots_description_m2">
    <rus>Бывший хозяин этой вещи был настоящим туристом и, видать, не раз хаживал в нём в тяжёлые, на грани человеческих возможностей, походы. Он знал, как правильно распределить груз, который нёс, и каким вещам отдать предпочтение. Карманы на куртке и грамотно подобранный рюкзак позволяют нести больший вес.</rus>
  </string>
  <string id="outfit_scientific_stalker_name">
    <rus>Комбинезон "СЕВА"</rus>
  </string>
  <string id="outfit_scientific_stalker_slots_name">
    <rus>Комбинезон "СЕВА" — Расширенный</rus>
  </string>
  <string id="outfit_scientific_stalker_plus_name">
    <rus>Комбинезон "СЕВА" — УВ-2</rus>
  </string>
  <string id="outfit_scientific_stalker_slotsplus_name">
    <rus>Комбинезон "СЕВА" — Расширенный УВ-2</rus>
  </string>
  <string id="outfit_scientific_stalker_description">
    <rus>Производимый одним из оборонных киевских НИИ, данный комбинезон предоставляет отличную альтернативу другим сталкерским комбинезонам, изготовленным в кустарных условиях. Представляет из себя отличное сочетание бронированного комбинезона, системы дыхания с замкнутым циклом, а также встроенной системы подавления действия аномальных полей. За счёт удачного подбора материалов является хорошим выбором. Единственный недостаток — его цена.</rus>
  </string>
  <string id="outfit_scientific_stalker_slots_description">
    <rus>Производимый одним из оборонных киевских НИИ, данный комбинезон предоставляет отличную альтернативу другим сталкерским комбинезонам, изготовленным в кустарных условиях. Представляет из себя отличное сочетание бронированного комбинезона, системы дыхания с замкнутым циклом, а также встроенной системы подавления действия аномальных полей. За счёт удачного подбора материалов является хорошим выбором. Единственный недостаток — его цена.</rus>
  </string>
  <string id="outfit_exoskeleton_broken_name">
    <rus>Повреждённый экзоскелет</rus>
  </string>
  <string id="outfit_exoskeleton_broken_description">
    <rus>Сильно б/у, но ещё способный послужить кому-нибудь экзоскелет. Главное достоинство — это его цена. Все характеристики сильно упали, поэтому крайне не рекомендуется для дальних вылазок.</rus>
  </string>
  <string id="outfit_freedom_light_name">
    <rus>Комбинезон "Ветер свободы"</rus>
  </string>
  <string id="outfit_freedom_light_slots_name">
    <rus>Комбинезон "Ветер свободы" — Расширенный</rus>
  </string>
  <string id="outfit_freedom_light_plus_name">
    <rus>Комбинезон "Ветер свободы" — УВ-1</rus>
  </string>
  <string id="outfit_freedom_light_slotsplus_name">
    <rus>Комбинезон "Ветер свободы" — Расширенный УВ-1</rus>
  </string>
  <string id="outfit_freedom_light_description">
    <rus>Производимый ремесленниками группировки "Свобода" облегчённый комбинезон сталкера. Лёгкий армейский бронежилет, плюс накладные усиливающие кевларовые пластины. Способен защитить от слабого оружия. Ткань комбинезона обработана специальным составом, повышающим сопротивление аномальной активности.</rus>
  </string>
  <string id="outfit_freedom_light_slots_description">
    <rus>Производимый ремесленниками группировки "Свобода" облегчённый комбинезон сталкера. Лёгкий армейский бронежилет, плюс накладные усиливающие кевларовые пластины. Способен защитить от слабого оружия. Ткань комбинезона обработана специальным составом, повышающим сопротивление аномальной активности.</rus>
  </string>
  <string id="outfit_svoboda_gaz_m1_name">
    <rus>Комбинезон "Ветер свободы" с противогазом</rus>
  </string>
  <string id="outfit_svoboda_gaz_m1_slots_name">
    <rus>Комбинезон "Ветер свободы" с противогазом — Расширенный</rus>
  </string>
  <string id="outfit_svoboda_gaz_m1_plus_name">
    <rus>Комбинезон "Ветер свободы" с противогазом — УВ-1</rus>
  </string>
  <string id="outfit_svoboda_gaz_m1_slotsplus_name">
    <rus>Комбинезон "Ветер свободы" с противогазом — Расширенный УВ-1</rus>
  </string>
  <string id="outfit_svoboda_gaz_m1_description">
    <rus>Производимый ремесленниками группировки "Свобода" облегчённый комбинезон сталкера. Лёгкий армейский бронежилет, плюс накладные усиливающие кевларовые пластины. Способен защитить от слабого оружия. Ткань комбинезона обработана специальным составом, повышающим сопротивление аномальной активности. Эта модификация имеет усиленную защиту от радиации и химических ожогов.</rus>
  </string>
  <string id="outfit_svoboda_gaz_m1_slots_description">
    <rus>Производимый ремесленниками группировки "Свобода" облегчённый комбинезон сталкера. Лёгкий армейский бронежилет, плюс накладные усиливающие кевларовые пластины. Способен защитить от слабого оружия. Ткань комбинезона обработана специальным составом, повышающим сопротивление аномальной активности. Эта модификация имеет усиленную защиту от радиации и химических ожогов.</rus>
  </string>
  <string id="outfit_freedom_heavy_name">
    <rus>Комбинезон "Страж свободы"</rus>
  </string>
  <string id="outfit_freedom_heavy_slots_name">
    <rus>Комбинезон "Страж свободы" — Расширенный</rus>
  </string>
  <string id="outfit_freedom_heavy_plus_name">
    <rus>Комбинезон "Страж свободы" — УВ-1</rus>
  </string>
  <string id="outfit_freedom_heavy_slotsplus_name">
    <rus>Комбинезон "Страж свободы" — Расширенный УВ-1</rus>
  </string>
  <string id="outfit_freedom_heavy_description">
    <rus>Производимый ремесленниками группировки "Свобода" усиленный комбинезон сталкера. Средний армейский бронежилет, плюс накладные усиливающие циркониевые элементы, дают неплохую защиту от автоматных пуль и осколков на различных дистанциях. Материал костюма состоит из двух слоёв: специально обработанной кожи и ткани с асбестовой нитью. Даёт некоторую защиту от различных аномальных воздействий и радиации.</rus>
  </string>
  <string id="outfit_freedom_heavy_slots_description">
    <rus>Производимый ремесленниками группировки "Свобода" усиленный комбинезон сталкера. Средний армейский бронежилет, плюс накладные усиливающие циркониевые элементы, дают неплохую защиту от автоматных пуль и осколков на различных дистанциях. Материал костюма состоит из двух слоёв: специально обработанной кожи и ткани с асбестовой нитью. Даёт некоторую защиту от различных аномальных воздействий и радиации.</rus>
  </string>
  <string id="svoboda_outfit_name_m1">
    <rus>Комбинезон "Грозовое эхо"</rus>
  </string>
  <string id="svoboda_outfit_m1_slots_name">
    <rus>Комбинезон "Грозовое эхо" — Расширенный</rus>
  </string>
  <string id="svoboda_outfit_m1_plus_name">
    <rus>Комбинезон "Грозовое эхо" — УВ-1</rus>
  </string>
  <string id="svoboda_outfit_m1_slotsplus_name">
    <rus>Комбинезон "Грозовое эхо" — Расширенный УВ-1</rus>
  </string>
  <string id="svoboda_outfit_description_m1">
    <rus>Этот костюм когда-то принадлежал известному свободовцу по прозвищу Дождь. Говорят, он попал в Зону после удара молнии во время очередного выброса, но каким-то чудом выжил. Возможно, это и повлияло на его снаряжение — комбинезон будто бы впитал энергию Зоны и теперь обладает повышенной защитой от электрических разрядов.</rus>
  </string>
  <string id="svoboda_outfit_slots_description_m1">
    <rus>Этот костюм когда-то принадлежал известному свободовцу по прозвищу Дождь. Говорят, он попал в Зону после удара молнии во время очередного выброса, но каким-то чудом выжил. Возможно, это и повлияло на его снаряжение — комбинезон будто бы впитал энергию Зоны и теперь обладает повышенной защитой от электрических разрядов.</rus>
  </string>
  <string id="outfit_scientific_freedom_name">
    <rus>Научный костюм "Свободы"</rus>
  </string>
  <string id="outfit_scientific_freedom_slots_name">
    <rus>Научный костюм "Свободы" — Расширенный</rus>
  </string>
  <string id="outfit_scientific_freedom_plus_name">
    <rus>Научный костюм "Свободы" — УВ-2</rus>
  </string>
  <string id="outfit_scientific_freedom_slotsplus_name">
    <rus>Научный костюм "Свободы" — Расширенный УВ-2</rus>
  </string>
  <string id="outfit_scientific_freedom_description">
    <rus>Производство группировки "Свобода" для научных исследований в Зоне. Система защиты с замкнутым циклом, встроенная система подавления действия аномальных полей. Высокая защита от радиации. Пулевая защита всё-таки недостаточна для активных боевых действий.</rus>
  </string>
  <string id="freedom_scientific_slots_outfit_description">
    <rus>Производство группировки "Свобода" для научных исследований в Зоне. Система защиты с замкнутым циклом, встроенная система подавления действия аномальных полей. Высокая защита от радиации. Пулевая защита всё-таки недостаточна для активных боевых действий.</rus>
  </string>
  <string id="outfit_exoskeleton_freedom_name">
    <rus>Экзоскелет "Свободы"</rus>
  </string>
  <string id="outfit_exoskeleton_freedom_slots_name">
    <rus>Экзоскелет "Свободы" — Расширенный</rus>
  </string>
  <string id="outfit_exoskeleton_freedom_plus_name">
    <rus>Экзоскелет "Свободы" — УВ-3</rus>
  </string>
  <string id="outfit_exoskeleton_freedom_slotsplus_name">
    <rus>Экзоскелет "Свободы" — Расширенный УВ-3</rus>
  </string>
  <string id="outfit_exoskeleton_freedom_description">
    <rus>Продукт кустарей из "Свободы". Экспериментируя с различными модификациями, им удалось создать действительно удачную конструкцию, хоть и после многочисленных попыток. По характеристиками раньше был сопоставим с костюмом "Долга", но "свободовским" кустарям всё-таки удалось сделать ряд отличительных черт. Режим бега активирован. При всём при этом, работы по совершенствованию костюма продолжаются.</rus>
  </string>
  <string id="outfit_exoskeleton_freedom_slots_description">
    <rus>Продукт кустарей из "Свободы". Экспериментируя с различными модификациями, им удалось создать действительно удачную конструкцию, хоть и после многочисленных попыток. По характеристиками раньше был сопоставим с костюмом "Долга", но "свободовским" кустарям всё-таки удалось сделать ряд отличительных черт. Режим бега активирован. При всём при этом, работы по совершенствованию костюма продолжаются.</rus>
  </string>
  <string id="outfit_gravisak_name">
    <rus>Уникальный гравикостюм</rus>
  </string>
  <string id="outfit_gravisak_slots_name">
    <rus>Уникальный гравикостюм — Расширенный</rus>
  </string>
  <string id="outfit_gravisak_plus_name">
    <rus>Уникальный гравикостюм — УВ-3</rus>
  </string>
  <string id="outfit_gravisak_slotsplus_name">
    <rus>Уникальный гравикостюм — Расширенный УВ-3</rus>
  </string>
  <string id="outfit_gravisak_description">
    <rus>Модифицированный с помощью антигравитационного артефакта "Булыжник" бронежилет. Позволяет переносить значительное кол-во груза, при этом в неактивном состоянии очень тяжёлый. К сожалению, в результате модификации приобрёл способность увеличивать повреждающие воздействия на организм.</rus>
  </string>
  <string id="outfit_gravisak_slots_description">
    <rus>Модифицированный с помощью антигравитационного артефакта "Булыжник" бронежилет. Позволяет переносить значительное кол-во груза, при этом в неактивном состоянии очень тяжёлый. К сожалению, в результате модификации приобрёл способность увеличивать повреждающие воздействия на организм.</rus>
  </string>
  <string id="outfit_exoskeleton_prototype_quest_name">
    <rus>Прототип экзоскелета</rus>
  </string>
  <string id="outfit_exoskeleton_prototype_quest_description">
    <rus>Первый прототип экзоскелета. Так и не был выпущен в серийное производство из-за дефектов в дизайне и некоторых технических недоработок.</rus>
  </string>
  <string id="outfit_exoskeleton_prototype_name">
    <rus>Экзоскелет "Mk.1"</rus>
  </string>
  <string id="outfit_exoskeleton_prototype_slots_name">
    <rus>Экзоскелет "Mk.1" — Расширенный</rus>
  </string>
  <string id="outfit_exoskeleton_prototype_plus_name">
    <rus>Экзоскелет "Mk.1" — УВ-3</rus>
  </string>
  <string id="outfit_exoskeleton_prototype_slotsplus_name">
    <rus>Экзоскелет "Mk.1" — Расширенный УВ-3</rus>
  </string>
  <string id="outfit_exoskeleton_prototype_description">
    <rus>Один из первых прототипов экзоскелета. Адаптирован специально для Зоны, но противогаз ещё старого советского образца. По сравнению с предсерийными образцами, характеристики заметно ниже.</rus>
  </string>
  <string id="outfit_exoskeleton_prototype_slots_description">
    <rus>Один из первых прототипов экзоскелета. Адаптирован специально для Зоны, но противогаз ещё старого советского образца. По сравнению с предсерийными образцами, характеристики заметно ниже.</rus>
  </string>
  <string id="outfit_sky_light_name">
    <rus>Комбинезон "Чистое небо"</rus>
  </string>
  <string id="outfit_sky_light_slots_name">
    <rus>Комбинезон "Чистое небо" — Расширенный</rus>
  </string>
  <string id="outfit_sky_light_plus_name">
    <rus>Комбинезон "Чистое небо" — УВ-1</rus>
  </string>
  <string id="outfit_sky_light_slotsplus_name">
    <rus>Комбинезон "Чистое небо" — Расширенный УВ-1</rus>
  </string>
  <string id="outfit_sky_light_description">
    <rus>Производимый ремесленниками группировки "Чистое небо" облегченный комбинезон сталкера. Лёгкий армейский бронежилет. Способен защитить от слабого оружия. Ткань комбинезона обработана специальным составом, повышающим сопротивление аномальной активности.</rus>
  </string>
  <string id="outfit_sky_light_slots_description">
    <rus>Производимый ремесленниками группировки "Чистое небо" облегченный комбинезон сталкера. Лёгкий армейский бронежилет. Способен защитить от слабого оружия. Ткань комбинезона обработана специальным составом, повышающим сопротивление аномальной активности.</rus>
  </string>
  <string id="outfit_sky_heavy_name">
    <rus>Комбинезон "Страж неба"</rus>
  </string>
  <string id="outfit_sky_heavy_slots_name">
    <rus>Комбинезон "Страж неба" — Расширенный</rus>
  </string>
  <string id="outfit_sky_heavy_plus_name">
    <rus>Комбинезон "Страж неба" — УВ-1</rus>
  </string>
  <string id="outfit_sky_heavy_slotsplus_name">
    <rus>Комбинезон "Страж неба" — Расширенный УВ-1</rus>
  </string>
  <string id="outfit_sky_heavy_description">
    <rus>Производимый ремесленниками группировки "Чистое небо" усиленный комбинезон сталкера. Средний армейский бронежилет. Материал костюма состоит из двух слоев: специально обработанной кожи и ткани с асбестовой нитью. Дает хорошую защиту от различных аномальных воздействий и радиации.</rus>
  </string>
  <string id="outfit_sky_heavy_slots_description">
    <rus>Производимый ремесленниками группировки "Чистое небо" усиленный комбинезон сталкера. Средний армейский бронежилет. Материал костюма состоит из двух слоев: специально обработанной кожи и ткани с асбестовой нитью. Дает хорошую защиту от различных аномальных воздействий и радиации.</rus>
  </string>
  <string id="outfit_exoskeleton_sky_name">
    <rus>Экзоскелет "Чистого неба"</rus>
  </string>
  <string id="outfit_exoskeleton_sky_slots_name">
    <rus>Экзоскелет "Чистого неба" — Расширенный</rus>
  </string>
  <string id="outfit_exoskeleton_sky_plus_name">
    <rus>Экзоскелет "Чистого неба" — УВ-3</rus>
  </string>
  <string id="outfit_exoskeleton_sky_slotsplus_name">
    <rus>Экзоскелет "Чистого неба" — Расширенный УВ-3</rus>
  </string>
  <string id="nebo_exo_description">
    <rus>Экзоскелет превосходно защищает от различных аномальных воздействий и радиации. Уязвим для бронебойных патронов. Очень редкий в Зоне костюм, который мало кто видел вживую. Впрочем, как и саму группировку...</rus>
  </string>
  <string id="nebo_exo_slots_description">
    <rus>Экзоскелет превосходно защищает от различных аномальных воздействий и радиации. Уязвим для бронебойных патронов. Очень редкий в Зоне костюм, который мало кто видел вживую. Впрочем, как и саму группировку...</rus>
  </string>
  <string id="outfit_scientific_sky_name">
    <rus>Научный костюм "Чистого неба"</rus>
  </string>
  <string id="outfit_scientific_sky_slots_name">
    <rus>Научный костюм "Чистого неба" — Расширенный</rus>
  </string>
  <string id="outfit_scientific_sky_plus_name">
    <rus>Научный костюм "Чистого неба" — УВ-2</rus>
  </string>
  <string id="outfit_scientific_sky_slotsplus_name">
    <rus>Научный костюм "Чистого неба" — Расширенный УВ-2</rus>
  </string>
  <string id="outfit_scientific_sky_description">
    <rus>Производство группировки "Чистое небо", для научных исследований в Зоне. Система защиты с замкнутым циклом, встроенная система подавления действия аномальных полей. Высокая защита от радиации. Пулевая защита всё-таки недостаточна для активных боевых действий.</rus>
  </string>
  <string id="outfit_scientific_sky_slots_description">
    <rus>Производство группировки "Чистое небо", для научных исследований в Зоне. Система защиты с замкнутым циклом, встроенная система подавления действия аномальных полей. Высокая защита от радиации. Пулевая защита всё-таки недостаточна для активных боевых действий.</rus>
  </string>
  <string id="outfit_monolit_black_name">
    <rus>Чёрный комбинезон "Монолита"</rus>
  </string>
  <string id="outfit_monolit_black_description">
    <rus>
    Элитный комбинезон сталкера группировки "Монолит", производитель неизвестен. Хоть по защитным характеристикам и уступает армейскому бронежилету серии "ПСЗ-9а", но зато у него есть один заметный плюс — в нём быстрее заживают раны и останавливается кровотечение. По структуре напоминает широко распространённые среди нейтральных сталкеров комбинезоны, в которых бронежилет соединяется с костюмом противорадиационной защиты. Неплохо защищает от слабого стрелкового оружия. Уровень защиты от аномальной активности оставляет желать лучшего из-за отсутствия системы фильтрации воздуха.</rus>
  </string>
  <string id="outfit_monolit_black_slotsplus_name">
    <rus>Чёрный комбинезон "Монолита" — Расширенный УВ-2</rus>
  </string>
  <string id="outfit_monolit_black_slots_description">
    <rus>
    Элитный комбинезон сталкера группировки "Монолит", производитель неизвестен. Хоть по защитным характеристикам и уступает армейскому бронежилету серии "ПСЗ-9а", но зато у него есть один заметный плюс — в нём быстрее заживают раны и останавливается кровотечение. По структуре напоминает широко распространённые среди нейтральных сталкеров комбинезоны, в которых бронежилет соединяется с костюмом противорадиационной защиты. Неплохо защищает от слабого стрелкового оружия. Уровень защиты от аномальной активности оставляет желать лучшего из-за отсутствия системы фильтрации воздуха.</rus>
  </string>
  <string id="outfit_psychiatrist_name">
    <rus>Плащ психиатра</rus>
  </string>
  <string id="outfit_psychiatrist_description">
    <rus>С виду — обычный бандитский плащ, только белого цвета — действительно похож на медицинский халат. Не обладает никакой защитой, имеет пониженную устойчивость к любым повреждениям и воздействиям (кроме телепатического), зато обладает одним замечательным свойством — способен до 100% снизить пси-воздействие контролёра. Тут и объяснять-то нечего, психиатры — люди особые... Кто владелец плаща и откуда у этого "халата" появилось такое замечательное свойство — загадка...</rus>
  </string>
  <string id="outfit_scientific_monolit_white_name">
    <rus>Костюм учёного "монолитовца"</rus>
  </string>
  <string id="outfit_scientific_monolit_white_description">
    <rus>Костюм, используемый боевиками "Монолита", участвующих в создании новых видов вооружения, реагентов и научного оборудования. За основу был взят укреплённый костюм эколога. Имеет белый цвет за счёт специального светоотражающего материала. Вшитые в него дополнительные сверхлёгкие защитные пластины, позволили повысить как устойчивость самого костюма, так и защиту его обладателя. В Зоне не распространён, так как создан в ограниченном количестве, и само существование такого костюма держится в секрете.</rus>
  </string>
  <string id="outfit_fireman_name">
    <rus>Костюм пожарного</rus>
  </string>
  <string id="outfit_fireman_description">
    <rus>Костюм получил своё название неслучайно — он был изготовлен сталкером, который когда-то действительно был пожарным. За основу взят обычный научный костюм, в котором было заменено стекло шлема и "подкладка". Жаропрочная ткань, используемая для этого, увеличила нагрузку на мышечную систему владельца — усталость в этом костюме наступает быстрее. Данный экземпляр не способен защитить хозяина от механических воздействий, радиации и телепатии, зато обладает неплохой защитой от химических реагентов, а самое главное — очень прилично защищает от воздействия огня. При износе костюма защитные свойства снижаются.</rus>
  </string>
  <string id="outfit_exoskeleton_specops_name">
    <rus>Военный экзоскелет</rus>
  </string>
  <string id="outfit_exoskeleton_specops_description">
    <rus>Экспериментальная разработка, созданная для спецподразделений, выполняющих операции в особо опасных районах. Этот экзоскелет сочетает в себе мощную бронезащиту и усиленные сервомоторы, позволяющие бойцу переносить тяжёлое снаряжение без потери подвижности. Улучшенные композитные пластины обеспечивают надёжную защиту от огнестрельного оружия, а интегрированная система жизнеобеспечения снижает воздействие радиации и химических веществ.</rus>
  </string>
  <string id="outfit_exoskeleton_black_doc_name">
    <rus>Экзоскелет Чёрного Доктора</rus>
  </string>
  <string id="outfit_exoskeleton_black_doc_description">
    <rus>Редкий и уникальный образец экзоскелета, покрытый чёрной защитной тканью. Используется охраной Чёрного Доктора – таинственной фигуры, известной среди сталкеров. Экзоскелет сильно модифицирован: он обладает усиленной системой сервоприводов, значительно увеличивающей мобильность владельца, при этом сохраняя отличную защиту от пуль и осколков. Кроме того, конструкция имеет встроенные фильтры, снижающие воздействие радиации и химических веществ. Мало кто знает, где и кем был создан этот экзоскелет, но его наличие в руках сталкера неизбежно привлекает внимание — как союзников, так и врагов.</rus>
  </string>
  <string id="outfit_specops_armor_name">
    <rus>Бронежилет спецназа</rus>
  </string>
  <string id="outfit_specops_armor_description">
    <rus>Элитный бронежилет, состоящий на вооружении специальных подразделений. Разработан для ведения боевых действий в условиях плотной застройки и экстремальной среды. Оснащён многослойной бронеплитой, обеспечивающей высокую степень защиты от огнестрельного оружия, а также дополнительными вставками, смягчающими удары и осколочные поражения. Благодаря продуманной эргономике и разгрузочной системе, бронежилет позволяет бойцу носить с собой большое количество боеприпасов и экипировки, не теряя мобильности. Однако его вес всё же остаётся ощутимым, а защита от аномальных воздействий минимальна.</rus>
  </string>
  <string id="outfit_scientific_nanosuit_name">
    <rus>Нанокостюм "Последнего дня"</rus>
  </string>
  <string id="outfit_scientific_nanosuit_description">
    <rus>Редкий экспериментальный нанокостюм, предположительно созданный в рамках закрытого проекта группировки "Последний день". В его основе лежит адаптивная наноткань с каркасом микросервоприводов, сочетающая серьёзную бронезащиту, герметизацию от радиации и химических угроз и высокую подвижность в бою. Композитные вставки эффективно гасят пули, осколки и часть ударных нагрузок, а встроенная электронная система непрерывно перераспределяет ресурсы костюма в зависимости от выбранного режима. \nНанокостюм поддерживает несколько профилей работы: броневой режим для максимальной защиты, скоростной для стремительного перемещения, силовой для усиления физических возможностей и маскировочный, снижающий заметность владельца. Все функции питаются от общего энергоблока, поэтому длительное использование продвинутых режимов требует контроля заряда и своевременного переключения между ними.</rus>
  </string>

  <!-- Headgear -->
    <string id="st_helm_bandana">
        <rus>Бандана</rus>
    </string>
    <string id="st_helm_bandana_descr">
        <rus>Обычная тканевая бандана. Часто используется военнослужащими у внутренних границ периметра. Может быть также использована и в качестве средства индивидуальной защиты, будучи обмотанной вокруг лица, в некоторой степени защищая от вдыхания токсичных или заражённых частиц. Тем не менее, при длительном использовании она склонна к накапливанию токсинов, поэтому крайне желательно всегда иметь запасную для быстрой замены.</rus>
    </string>

    <string id="st_helm_rp_bala">
        <rus>Балаклава</rus>
    </string>
    <string id="st_helm_rp_bala_descr">
        <rus>Обычная балаклава из чёрной ткани. Из приятных плюсов стоит отметить некоторый комфорт при ношении балаклавы зимой. Несмотря на то, что подобный кусок ткани ничуть не хуже обычных марлевых повязок, используемых сталкерами, он не обеспечивает должной защиты, а при длительном использовании и вовсе накапливает токсины. Поэтому крайне желательно всегда иметь запасную для быстрой замены.</rus>
    </string>

    <string id="st_helm_cloth_mask">
        <rus>Тряпичная маска</rus>
    </string>
    <string id="st_helm_cloth_mask_descr">
        <rus>Простой кусок ткани, свёрнутый в маску. Она часто используется сталкерами для предотвращения попадания в организм опасных частиц, в виде меры предосторожности. При длительном использовании маска может накапливать токсины, таким образом, желательно всегда иметь запасную для быстрой замены.</rus>
    </string>

    <string id="st_helm_resp">
        <rus>Респиратор</rus>
    </string>
    <string id="st_helm_resp_descr">
        <rus>Обыкновенный респиратор, каких много. Используется как новичками, так и ветеранами группировок из-за своей дешевизны, малого веса и доступности. И хотя подобный респиратор может защитить от радиоактивной пыли, от куда более серьёзных уровней радиационного заражения он точно не спасёт. К тому же респиратор практически не даёт никакой защиты от физических повреждений.</rus>
    </string>

    <string id="st_helm_respirator">
        <rus>Противогаз ПБФ</rus>
    </string>
    <string id="st_helm_respirator_descr">
        <rus>Шлем-маска ШМБ с дополнительными 40-мм фильтрами для большей функциональности. Поскольку процесс переоборудования из старых внутренних фильтров "Хомяка" так и не был стандартизирован, среди отдельных противогазов возможны отличия общего веса маски и показателей противорадиационной защиты. Как правило, подобные маски обеспечивают существенную защиту в зонах повышенной радиоактивности, однако крайне неэффективны и склонны к отказам в работе фильтров в зонах высокой токсичности, быстро приходя в полную негодность. Кроме того, они практически не дают никакой защиты от физических повреждений.</rus>
    </string>

    <string id="st_helm_respirator_m">
        <rus>Противогаз ПБФ-М</rus>
    </string>
    <string id="st_helm_respirator_m_descr">
        <rus>Шлем-маска ШМБ с дополнительными 40-мм фильтрами для большей функциональности и модернизированный уже в условиях Зоны. Поскольку процесс переоборудования из старых внутренних фильтров "Хомяка" так и не был стандартизирован, среди отдельных противогазов возможны отличия общего веса маски и показателей противорадиационной защиты. Как правило, подобные маски обеспечивают существенную защиту в зонах повышенной радиоактивности, однако крайне неэффективны и склонны к отказам в работе фильтров в зонах высокой токсичности, быстро приходя в полную негодность. Кроме того, они практически не дают никакой защиты от физических повреждений. В ходе модернизации на маску установили полноценный визор из упрочнённого стекла.</rus>
    </string>

    <string id="st_helm_m40">
        <rus>Противогаз M40</rus>
    </string>
    <string id="st_helm_m40_descr">
        <rus>Данный противогаз стоит на вооружении армии США, а также крайне популярен среди наёмников. Представляет собой маску противогаза и многослойный 40-миллиметровый дыхательный фильтр. M40 обеспечивает хорошую защиту во время пребывания в химически- и радиационно-загрязнённой среде даже при частичном повреждении маски.</rus>
    </string>

    <string id="st_helm_hardhat">
        <rus>Стальной шлем</rus>
    </string>
    <string id="st_helm_hardhat_descr">
        <rus>Чрезвычайно устаревший армейский стальной шлем с подвижным забралом для защиты глаз. Не обеспечивает должной защиты от аномалий или радиации, однако способен отрекошетить пулю при её попадании. Спросом в Зоне пользовался только в период первых столкновений между группировками.</rus>
    </string>

    <string id="st_helm_tactic">
        <rus>Шлем "Сфера 07"</rus>
    </string>
    <string id="st_helm_tactic_descr">
        <rus>Современный высококачественный шлем западного образца. Конструкция состоит из нескольких слоёв кевлара для защиты владельца от тяжёлых физических повреждений. Сам же шлем сделан из композиционных диэлектрических материалов, предоставляющих гораздо лучшую защиту владельцу от воздействия электрического тока по сравнению с большинством своих конкурентов. Достаточно распространён среди военных сталкеров и спецназа, которые зачастую используют шлем вместе с бронекостюмами серии ПСЗ.</rus>
    </string>

    <string id="st_helm_tactic_m">
        <rus>Шлем "Сфера 08"</rus>
    </string>
    <string id="st_helm_tactic_m_descr">
        <rus>Современный высококачественный шлем западного образца со встроенной системой фильтрации воздуха. Конструкция состоит из нескольких слоёв кевлара для защиты владельца от тяжёлых физических повреждений. Сам же шлем сделан из композиционных диэлектрических материалов, предоставляющих гораздо лучшую защиту владельцу от воздействия электрического тока по сравнению с большинством своих конкурентов. Достаточно распространён среди военных сталкеров и спецназа, которые зачастую используют шлем вместе с бронекостюмами серии ПСЗ.</rus>
    </string>

    <string id="st_helm_battle">
        <rus>Шлем "Сфера М12"</rus>
    </string>
    <string id="st_helm_battle_descr">
        <rus>Отделанный камуфлированной тканью алюминиево-титановый шлем с карманами для стальных бронеэлементов и оснащённый бронемаской. Достаточно распространён среди военных сталкеров и спецназа, которые зачастую используют данный шлем вместе с бронекостюмами серии ПСЗ. В целом, "М12" является одним из лучших представителей боевых шлемов в Зоне, а также желанным элементом защитной экипировки среди обеспеченных сталкеров, которые ценят свою жизнь в бою.</rus>
    </string>

    <string id="st_helm_protective">
        <rus>Шлем ССП-99 "Заслон"</rus>
    </string>
    <string id="st_helm_protective_descr">
        <rus>Неудобный, однако высококачественный шлем-капюшон, производимый всё тем же самым НИИ, ответственным также и за создание комбинезонов серии "СЕВА". Имеет герметичную конструкцию, предназначенную для полной изоляции от условий аномальной среды. Может быть использован в сочетании с армейскими бронекостюмами, чтобы повысить эффективность их защиты в аномальных зонах. Также используется в защитных комбинезонах ССП.</rus>
    </string>

    <string id="st_helm_exo_name">
        <rus>Экзошлем</rus>
    </string>
    <string id="st_helm_exo_descr">
        <rus>Специальный шлем для экзоскелета, рассчитанный на тяжёлые условия Зоны. Данный шлем имеет хорошую защиту от пулевых ранений, а в сочетании ещё и с защитой от аномальных воздействий, делает его одним из лучших в своей ценовой категории.</rus>
    </string>

  <!-- НЕ ИСПОЛЬЗУЕТСЯ -->
    <string id="st_helm_respirator_gp5">
        <rus>Противогаз ГП-5</rus>
    </string>
    <string id="st_helm_respirator_gp5_descr">
        <rus>Противогаз ГП-5 предназначался для защиты гражданского населения Советского Союза от выпадения радиоактивных осадков и изготавливался в период Холодной войны с 1962 по 1989 год.\nПредставляет собой шлем-маску из белой и чёрной резины, линзы которой удерживаются на месте обжимным ободами. Фильтры же были аккуратно либо восстановлены, либо заменены. По сравнению с комплектами противогазов схожей ценовой категории, например, ПБФ, ГП-5 может похвастаться не только большей защитой от радиации, но и столь же высокой неэффективностью работы в токсичной среде.</rus>
    </string>

    <string id="st_helm_metro">
        <rus>Шлем-противогаз ПД</rus>
    </string>
    <string id="st_helm_metro_descr">
        <rus>Очень напоминает чешский противогаз M10, дополнительно укреплённый бронепластинами. Считается, что за его созданием стоит группировка "Последний день", отчего он и получил множество вариантов своего названия: "ПД", "Последний день", "шлем апокалипсиса" и т.п. Несмотря на то, что противогаз крайне неудобен для ношения, он может похвастаться достаточно высокими показателями химической, радиационной и физической защит. После того, как лидер группировки "Последний день" был убит сталкером по прозвищу Призрак, а сама группировка распалась, сохранившиеся копии шлемов быстро попали в пользование тогдашних рядовых сталкеров. Но по-настоящему особую популярность M10 возымел среди личностей, желающих получить доступ к секретным подземным лабораториям на территории Зоны.</rus>
    </string>

    <string id="st_helm_spartan">
        <rus>Шлем M10 "Спартанец"</rus>
    </string>
    <string id="st_helm_spartan_descr">
        <rus>Баллистический шлем на основе шлема ПД ("Последний день"), сделанный по заказу ряда влиятельных сталкеров. По сравнению с оригиналом отличается не только лёгкостью, но и куда более продвинутыми защитными характеристиками. А благодаря наличию противоаномальной защиты, ещё и выгодно отличается от таких представителей боевых шлемов, как "Сфера", что делает его крайне популярным среди сталкеров, которые могут себе его позволить.</rus>
    </string>

    <string id="st_helm_ach7">
        <rus>Шлем ACH-7</rus>
    </string>
    <string id="st_helm_ach7_descr">
        <rus>Усовершенствованный комплект защиты головы со семью частями — ACH-7 (Advanced Compound Headgear, 7 Parts) — это куда более современная версия стального шлема. Несмотря на то, что он хорошо проявляет себя при защите от осколков, главная же его привлекательность — это устойчивость к пси-воздействию и на удивление низкая стоимость. Тем не менее, отсутствие какого-либо респираторного устройства индивидуальной защиты делает его крайне неудачным выбором для использования в суровых условиях Зоны. Поэтому популярен среди сталкеров-новичков, которые не рискуют лезть на заражённые территории, однако всё же готовы проверить на прочность своё психическое здоровье.</rus>
    </string>

    <string id="st_helm_ach7ex">
        <rus>Шлем ACH-7EX</rus>
    </string>
    <string id="st_helm_ach7ex_descr">
        <rus>Данный экземпляр представляет собой расширенную версию оригинального ACH-7. Главным отличием от основной версии является наличие респираторного устройства индивидуальной защиты. Уровень защиты от токсичных веществ и радиации находится где-то между таковыми противогазов ГП-5 и ПБФ, а благодаря наличию шлема даёт ещё и хорошую защиту от физических воздействий. Крайне популярен среди сталкеров, которым нужна хорошая сбалансированная защита по приемлемой цене.</rus>
    </string>

    <string id="st_helm_ppm88">
        <rus>Противогаз ППМ-88</rus>
    </string>
    <string id="st_helm_ppm88_descr">
        <rus>Российский противогаз ППМ-88, крайне хорошо проявляющий себя в условиях РХБ-угроз. В условиях Зоны считается духовным наследником ГП-5 благодаря схожим защитным характеристикам вдобавок к существенно улучшенным показателям защиты против химических и радиационных угроз. Неплохой выбор среди сталкеров для своих повседневных вылазок в "грязные" места с учётом того, что обладатели противогаза стараются избегать боевых действий или переоценивать его возможности.</rus>
    </string>

    <string id="st_helm_m50">
        <rus>Противогаз M50з</rus>
    </string>
    <string id="st_helm_m50_descr">
        <rus>Противогаз M50, специально модифицированный для лучшей функциональности в условиях Зоны. И пусть результатом этих манипуляций стали сниженные показатели защиты по сравнению с оригиналом, модификация "З" определённо может похвастаться хорошей защитой от пси-излучения и радиации. Можно сказать, что данный представитель противогазов является улучшенной версией M40, и, в отличие от последнего, приобретается напрямую представителями ЧВК, которые снабжают ими своих оперативников в Зоне или же перепродают другим группам наёмников.</rus>
    </string>

    <string id="st_helm_ranger">
        <rus>Противогаз ГП-10Р</rus>
    </string>
    <string id="st_helm_ranger_descr">
        <rus>Будучи сконструированным на базе ГП-10, данный противогаз был создан с целью обеспечения защиты владельца от пси-воздействия контролёров и полтергейстов. И хотя результаты, мягко говоря, неоднозначные, данная модель остаётся отличным вариантом для тех, кто нуждается в дополнительной защите от осколков, а также пси- и термических угроз.</rus>
    </string>

  <!-- Backpack -->
    <string id="st_itm_backpack_name">
        <rus>Базовый рюкзак</rus>
    </string>
    <string id="st_itm_backpack_desc">
        <rus>Простой рюкзак без опознавательных знаков. Потёртый, но ещё послужит — особенно тому, кто знает толк в выживании.</rus>
    </string>

    <string id="st_itm_backpack_stalker_name">
        <rus>Рюкзак сталкера</rus>
    </string>
    <string id="st_itm_backpack_stalker_desc">
        <rus>Типичный рюкзак из снаряжения нейтральных сталкеров. Потёртый, но ещё послужит — особенно тому, кто знает толк в выживании.</rus>
    </string>

    <string id="st_itm_backpack_bandit_name">
        <rus>Рюкзак бандита</rus>
    </string>
    <string id="st_itm_backpack_bandit_desc">
        <rus>Типичный рюкзак из снаряжения бандитов. Потёртый, но ещё послужит — особенно тому, кто знает толк в выживании.</rus>
    </string>

    <string id="st_itm_backpack_army_name">
        <rus>Рюкзак военного</rus>
    </string>
    <string id="st_itm_backpack_army_desc">
        <rus>Типичный рюкзак из снаряжения военных. Потёртый, но ещё послужит — особенно тому, кто знает толк в выживании.</rus>
    </string>

    <string id="st_itm_backpack_killer_name">
        <rus>Рюкзак наёмника</rus>
    </string>
    <string id="st_itm_backpack_killer_desc">
        <rus>Типичный рюкзак из снаряжения наёмников. Потёртый, но ещё послужит — особенно тому, кто знает толк в выживании.</rus>
    </string>

    <string id="st_itm_backpack_dolg_name">
        <rus>Рюкзак "Долга"</rus>
    </string>
    <string id="st_itm_backpack_dolg_desc">
        <rus>Типичный рюкзак из снаряжения группировки "Долг". Потёртый, но ещё послужит — особенно тому, кто знает толк в выживании.</rus>
    </string>

    <string id="st_itm_backpack_freedom_name">
        <rus>Рюкзак "Свободы"</rus>
    </string>
    <string id="st_itm_backpack_freedom_desc">
        <rus>Типичный рюкзак из снаряжения группировки "Свобода". Потёртый, но ещё послужит — особенно тому, кто знает толк в выживании.</rus>
    </string>

    <string id="st_itm_backpack_csky_name">
        <rus>Рюкзак "Чистого неба"</rus>
    </string>
    <string id="st_itm_backpack_csky_desc">
        <rus>Типичный рюкзак из снаряжения группировки "Чистое небо". Потёртый, но ещё послужит — особенно тому, кто знает толк в выживании.</rus>
    </string>

    <string id="st_itm_backpack_monolith_name">
        <rus>Рюкзак "Монолита"</rus>
    </string>
    <string id="st_itm_backpack_monolith_desc">
        <rus>Типичный рюкзак из снаряжения группировки "Монолит". Потёртый, но ещё послужит — особенно тому, кто знает толк в выживании.</rus>
    </string>

    <string id="st_itm_backpack_vkbo_name">
        <rus>Армейский вещмешок ВКБО</rus>
    </string>
    <string id="st_itm_backpack_vkbo_desc">
        <rus>Стандартный рюкзак из комплекта экипировки солдата. Простой по конструкции, вместительный, рассчитан на длительные переходы. Часто используется не только военными, но и сталкерами, ценящими надёжность и запас прочности.</rus>
    </string>

    <string id="st_itm_backpack_group99_name">
        <rus>Рюкзак Группа 99 "Т20" (Умбра)</rus>
    </string>
    <string id="st_itm_backpack_group99_desc">
        <rus>Тактический рюкзак "Т20" (Умбра) от компании "Группа 99". Оснащён модульной системой креплений MOLLE, хорошо распределяет нагрузку и надёжен в эксплуатации. Высоко ценится опытными бойцами и разведчиками за универсальность и эргономику.</rus>
    </string>

    <string id="st_itm_backpack_ana_name">
        <rus>Боевой ранец ANA Tactical "Бета 2" (Олива)</rus>
    </string>
    <string id="st_itm_backpack_ana_desc">
        <rus>Боевой рюкзак ANA Tactical "Бета 2" в расцветке "Олива" — один из самых популярных в силовых структурах. Имеет несколько отсеков, модульную конструкцию и прочные материалы. Создан с упором на функциональность в бою и автономных операциях.</rus>
    </string>

    <string id="st_itm_backpack_mystery_name">
        <rus>Рюкзак Mystery Ranch</rus>
    </string>
    <string id="st_itm_backpack_mystery_desc">
        <rus>Премиальное снаряжение от американского производителя, известного качеством и продуманностью дизайна. Используется как военными, так и альпинистами. Отличается высокой эргономикой, надёжной фурнитурой и стойкостью к нагрузкам.</rus>
    </string>

</string_table>